MANIFEST.in
setup.py
pytenpay/__init__.py
pytenpay/_private.bak
pytenpay/_private.py
pytenpay/_private.pyc
pytenpay/cacert.pem
pytenpay/new.pem
pytenpay/template.py
pytenpay/template.pyc
pytenpay/tenpay.pem
pytenpay/tenpay.py
pytenpay/view.py
pytenpay.egg-info/PKG-INFO
pytenpay.egg-info/SOURCES.txt
pytenpay.egg-info/dependency_links.txt
pytenpay.egg-info/not-zip-safe
pytenpay.egg-info/requires.txt
pytenpay.egg-info/top_level.txt