Metadata-Version: 1.0
Name: pytenpay
Version: 0.3.0
Summary: 财付通批量银行代付接口Python实现
Home-page: https://bitbucket.org/lerry/pytenpay
Author: Zuroc, Lerry
Author-email: lvdachao@gmail.com
License: UNKNOWN
Platform: UNKNOWN
